onionpp
