Metadata-Version: 2.1
Name: onionpp
Version: 0.12
Summary: embed tor into your application
Home-page: https://github.com/nbdy/onionpp
Author: Pascal Eberlein
Author-email: pascal@eberlein.io
License: MIT
Project-URL: Gitbub, https://github.com/nbdy/onionpp
Keywords: embed,tor
Platform: UNKNOWN
Classifier: Intended Audience :: Developers
Classifier: Topic :: Software Development :: Libraries :: Python Modules
Classifier: Topic :: Utilities
Classifier: Programming Language :: C++
Classifier: Programming Language :: Python :: 3 :: Only
Classifier: Programming Language :: Python :: 3.6
Classifier: Programming Language :: Python :: 3.7
Classifier: Programming Language :: Python :: 3.8
Classifier: Programming Language :: Python :: 3.9
Classifier: Programming Language :: Python :: 3.10
Classifier: License :: OSI Approved :: MIT License
Classifier: Programming Language :: C++
Classifier: Topic :: Software Development :: Libraries :: Python Modules
Requires-Python: >=3.6
